life360/__init__.py
life360/api.py
life360/const.py
life360/exceptions.py
life360/version.py
life360-7.0.1.dist-info/LICENSE
life360-7.0.1.dist-info/METADATA
life360-7.0.1.dist-info/WHEEL
life360-7.0.1.dist-info/top_level.txt
life360-7.0.1.dist-info/RECORD
