Metadata-Version: 2.1
Name: life360
Version: 7.0.1
Summary: Life360 Communications Module
Home-page: https://github.com/pnbruckner/life360
Author: Phil Bruckner
Author-email: pnbruckner@gmail.com
Classifier: Programming Language :: Python :: 3
Classifier: License :: OSI Approved :: MIT License
Classifier: Operating System :: OS Independent
License-File: LICENSE
Requires-Dist: aiohttp
